{
  "CumulativeLatAvg": ".CumulativeLatAvg.",
  "CumulativeLatMax": ".CumulativeLatMax.",
  "CumulativeLatMin": ".CumulativeLatMin.",
  "CumulativePct95": ".CumulativePct95.",
  "CumulativePct99": ".CumulativePct99.",
  "CumulativeThroughput": ".CumulativeThroughput.",
  "CumulativeTotalOps": ".CumulativeTotalOps.",
  "IntervalLatAvg": ".IntervalLatAvg.",
  "IntervalLatMax": ".IntervalLatMax.",
  "IntervalLatMin": ".IntervalLatMin.",
  "IntervalPct95": ".IntervalPct95.",
  "IntervalPct99": ".IntervalPct99.",
  "IntervalThroughpu": ".IntervalThroughput.",
  "IntervalTotalOps": ".IntervalTotalOps.",
  "MultiCumulativeLatAvg": ".MultiCumulativeLatAvg.",
  "MultiCumulativeLatMax": ".MultiCumulativeLatMax.",
  "MultiCumulativeLatMin": ".MultiCumulativeLatMin.",
  "MultiCumulativePct95": ".MultiCumulativePct95.",
  "MultiCumulativePct99": ".MultiCumulativePct99.",
  "MultiCumulativeThroughput": ".MultiCumulativeThroughput.",
  "MultiCumulativeTotalOps": ".MultiCumulativeTotalOps.",
  "MultiIntervalLatAvg": ".MultiIntervalLatAvg.",
  "MultiIntervalLatMax": ".MultiIntervalLatMax.",
  "MultiIntervalLatMin": ".MultiIntervalLatMin.",
  "MultiIntervalPct95": ".MultiIntervalPct95.",
  "MultiIntervalPct99": ".MultiIntervalPct99.",
  "MultiIntervalThroughput": ".MultiIntervalThroughput.",
  "MultiIntervalTotalOps": ".MultiIntervalTotalOps."
}